explicit_implementation/__init__.py
explicit_implementation/decorators.py
explicit_implementation/interface.py
explicit_implementation/py.typed
explicit_implementation-0.1.1.dist-info/METADATA
explicit_implementation-0.1.1.dist-info/WHEEL
explicit_implementation-0.1.1.dist-info/licenses/LICENSE
explicit_implementation-0.1.1.dist-info/RECORD
