Metadata-Version: 2.4
Name: explicit-implementation
Version: 0.1.1
Summary: A Python library for explicit interface implementations with compile-time safety
Project-URL: Homepage, https://github.com/xpodev/explicit-implementation
Project-URL: Repository, https://github.com/xpodev/explicit-implementation
Project-URL: Issues, https://github.com/xpodev/explicit-implementation/issues
Author-email: Binyamin Y Cohen <biny@xpo.dev>
License: MIT
License-File: LICENSE
Keywords: abc,explicit,implementation,interface,typing
Classifier: Development Status :: 4 - Beta
Classifier: Intended Audience :: Developers
Classifier: License :: OSI Approved :: MIT License
Classifier: Operating System :: OS Independent
Classifier: Programming Language :: Python :: 3
Classifier: Programming Language :: Python :: 3.10
Classifier: Programming Language :: Python :: 3.11
Classifier: Programming Language :: Python :: 3.12
Classifier: Programming Language :: Python :: 3.13
Classifier: Topic :: Software Development :: Libraries :: Python Modules
Classifier: Topic :: Software Development :: Object Brokering
Classifier: Typing :: Typed
Requires-Python: >=3.10
